json_to_github_actions.py
json_to_github_actions-1.1.1.dist-info/METADATA
json_to_github_actions-1.1.1.dist-info/WHEEL
json_to_github_actions-1.1.1.dist-info/entry_points.txt
json_to_github_actions-1.1.1.dist-info/top_level.txt
json_to_github_actions-1.1.1.dist-info/RECORD
