Metadata-Version: 2.1
Name: json-to-github-actions
Version: 1.1.1
Requires-Dist: PyYAML
Requires-Dist: access-github
